[{"query":"大尾篤燒烤","value":1364550,"formattedValue":"飆升","link":"/trends/explore?q=%E5%A4%A7+%E5%B0%BE+%E7%AF%A4+%E7%87%92%E7%83%A4&date=2004-01-1+2019-04-11&geo=HK"},{"query":"燒烤","value":1294750,"formattedValue":"飆升","link":"/trends/explore?q=%E7%87%92%E7%83%A4&date=2004-01-1+2019-04-11&geo=HK"},{"query":"大尾篤燒烤王","value":674450,"formattedValue":"飆升","link":"/trends/explore?q=%E5%A4%A7+%E5%B0%BE+%E7%AF%A4+%E7%87%92%E7%83%A4+%E7%8E%8B&date=2004-01-1+2019-04-11&geo=HK"},{"query":"燒烤王","value":627450,"formattedValue":"飆升","link":"/trends/explore?q=%E7%87%92%E7%83%A4+%E7%8E%8B&date=2004-01-1+2019-04-11&geo=HK"},{"query":"單車","value":469650,"formattedValue":"飆升","link":"/trends/explore?q=%E5%96%AE%E8%BB%8A&date=2004-01-1+2019-04-11&geo=HK"},{"query":"大尾篤單車","value":416750,"formattedValue":"飆升","link":"/trends/explore?q=%E5%A4%A7+%E5%B0%BE+%E7%AF%A4+%E5%96%AE%E8%BB%8A&date=2004-01-1+2019-04-11&geo=HK"},{"query":"大尾篤燒烤場","value":287100,"formattedValue":"飆升","link":"/trends/explore?q=%E5%A4%A7+%E5%B0%BE+%E7%AF%A4+%E7%87%92%E7%83%A4+%E5%A0%B4&date=2004-01-1+2019-04-11&geo=HK"},{"query":"燒烤場","value":268700,"formattedValue":"飆升","link":"/trends/explore?q=%E7%87%92%E7%83%A4+%E5%A0%B4&date=2004-01-1+2019-04-11&geo=HK"},{"query":"大尾篤麥師傅","value":216200,"formattedValue":"飆升","link":"/trends/explore?q=%E5%A4%A7+%E5%B0%BE+%E7%AF%A4+%E9%BA%A5+%E5%B8%AB%E5%82%85&date=2004-01-1+2019-04-11&geo=HK"},{"query":"大尾篤租單車","value":153750,"formattedValue":"飆升","link":"/trends/explore?q=%E5%A4%A7+%E5%B0%BE+%E7%AF%A4+%E7%A7%9F+%E5%96%AE%E8%BB%8A&date=2004-01-1+2019-04-11&geo=HK"},{"query":"bbq","value":112250,"formattedValue":"飆升","link":"/trends/explore?q=bbq&date=2004-01-1+2019-04-11&geo=HK"},{"query":"大尾篤巴士","value":111700,"formattedValue":"飆升","link":"/trends/explore?q=%E5%A4%A7+%E5%B0%BE+%E7%AF%A4+%E5%B7%B4%E5%A3%AB&date=2004-01-1+2019-04-11&geo=HK"},{"query":"大尾篤交通","value":73900,"formattedValue":"飆升","link":"/trends/explore?q=%E5%A4%A7+%E5%B0%BE+%E7%AF%A4+%E4%BA%A4%E9%80%9A&date=2004-01-1+2019-04-11&geo=HK"},{"query":"大尾篤水上活動中心","value":55600,"formattedValue":"飆升","link":"/trends/explore?q=%E5%A4%A7+%E5%B0%BE+%E7%AF%A4+%E6%B0%B4%E4%B8%8A+%E6%B4%BB%E5%8B%95+%E4%B8%AD%E5%BF%83&date=2004-01-1+2019-04-11&geo=HK"},{"query":"大尾篤燒烤樂園","value":55000,"formattedValue":"飆升","link":"/trends/explore?q=%E5%A4%A7+%E5%B0%BE+%E7%AF%A4+%E7%87%92%E7%83%A4+%E6%A8%82%E5%9C%92&date=2004-01-1+2019-04-11&geo=HK"},{"query":"單車徑","value":49750,"formattedValue":"飆升","link":"/trends/explore?q=%E5%96%AE%E8%BB%8A+%E5%BE%91&date=2004-01-1+2019-04-11&geo=HK"},{"query":"大圍租單車","value":43350,"formattedValue":"飆升","link":"/trends/explore?q=%E5%A4%A7+%E5%9C%8D+%E7%A7%9F+%E5%96%AE%E8%BB%8A&date=2004-01-1+2019-04-11&geo=HK"},{"query":"taimeituk","value":37250,"formattedValue":"飆升","link":"/trends/explore?q=tai+mei+tuk&date=2004-01-1+2019-04-11&geo=HK"}]