[{"query":"秀茂坪商場","value":584800,"formattedValue":"飆升","link":"/trends/explore?q=%E7%A7%80+%E8%8C%82+%E5%9D%AA+%E5%95%86%E5%A0%B4&date=2004-01-1+2019-04-11&geo=HK"},{"query":"秀茂坪小學","value":453900,"formattedValue":"飆升","link":"/trends/explore?q=%E7%A7%80+%E8%8C%82+%E5%9D%AA+%E5%B0%8F%E5%AD%B8&date=2004-01-1+2019-04-11&geo=HK"},{"query":"秀茂坪天主教小學","value":345700,"formattedValue":"飆升","link":"/trends/explore?q=%E7%A7%80+%E8%8C%82+%E5%9D%AA+%E5%A4%A9%E4%B8%BB%E6%95%99+%E5%B0%8F%E5%AD%B8&date=2004-01-1+2019-04-11&geo=HK"},{"query":"秀茂坪圖書館","value":62900,"formattedValue":"飆升","link":"/trends/explore?q=%E7%A7%80+%E8%8C%82+%E5%9D%AA+%E5%9C%96%E6%9B%B8+%E9%A4%A8&date=2004-01-1+2019-04-11&geo=HK"},{"query":"秀茂坪戲院","value":51600,"formattedValue":"飆升","link":"/trends/explore?q=%E7%A7%80+%E8%8C%82+%E5%9D%AA+%E6%88%B2%E9%99%A2&date=2004-01-1+2019-04-11&geo=HK"},{"query":"將軍澳","value":51550,"formattedValue":"飆升","link":"/trends/explore?q=%E5%B0%87%E8%BB%8D%E6%BE%B3&date=2004-01-1+2019-04-11&geo=HK"},{"query":"saumauping","value":46300,"formattedValue":"飆升","link":"/trends/explore?q=sau+mau+ping&date=2004-01-1+2019-04-11&geo=HK"},{"query":"1a","value":41150,"formattedValue":"飆升","link":"/trends/explore?q=1a&date=2004-01-1+2019-04-11&geo=HK"},{"query":"安達邨","value":35850,"formattedValue":"飆升","link":"/trends/explore?q=%E5%AE%89%E9%81%94+%E9%82%A8&date=2004-01-1+2019-04-11&geo=HK"}]