[{"query":"萬宜水庫","value":2643850,"formattedValue":"飆升","link":"/trends/explore?q=%E8%90%AC+%E5%AE%9C+%E6%B0%B4%E5%BA%AB&date=2004-01-1+2019-04-11&geo=HK"},{"query":"萬宜水庫東壩","value":869350,"formattedValue":"飆升","link":"/trends/explore?q=%E8%90%AC+%E5%AE%9C+%E6%B0%B4%E5%BA%AB+%E6%9D%B1+%E5%A3%A9&date=2004-01-1+2019-04-11&geo=HK"},{"query":"西貢","value":411300,"formattedValue":"飆升","link":"/trends/explore?q=%E8%A5%BF%E8%B2%A2&date=2004-01-1+2019-04-11&geo=HK"},{"query":"西貢萬宜水庫","value":405150,"formattedValue":"飆升","link":"/trends/explore?q=%E8%A5%BF%E8%B2%A2+%E8%90%AC+%E5%AE%9C+%E6%B0%B4%E5%BA%AB&date=2004-01-1+2019-04-11&geo=HK"},{"query":"萬宜水庫交通","value":328100,"formattedValue":"飆升","link":"/trends/explore?q=%E8%90%AC+%E5%AE%9C+%E6%B0%B4%E5%BA%AB+%E4%BA%A4%E9%80%9A&date=2004-01-1+2019-04-11&geo=HK"},{"query":"萬宜水庫西壩","value":222750,"formattedValue":"飆升","link":"/trends/explore?q=%E8%90%AC+%E5%AE%9C+%E6%B0%B4%E5%BA%AB+%E8%A5%BF+%E5%A3%A9&date=2004-01-1+2019-04-11&geo=HK"},{"query":"萬宜水庫行山","value":217750,"formattedValue":"飆升","link":"/trends/explore?q=%E8%90%AC+%E5%AE%9C+%E6%B0%B4%E5%BA%AB+%E8%A1%8C+%E5%B1%B1&date=2004-01-1+2019-04-11&geo=HK"},{"query":"萬宜水庫東壩交通","value":108800,"formattedValue":"飆升","link":"/trends/explore?q=%E8%90%AC+%E5%AE%9C+%E6%B0%B4%E5%BA%AB+%E6%9D%B1+%E5%A3%A9+%E4%BA%A4%E9%80%9A&date=2004-01-1+2019-04-11&geo=HK"},{"query":"地質公園","value":92200,"formattedValue":"飆升","link":"/trends/explore?q=%E5%9C%B0%E8%B3%AA+%E5%85%AC%E5%9C%92&date=2004-01-1+2019-04-11&geo=HK"},{"query":"船灣淡水湖","value":54050,"formattedValue":"飆升","link":"/trends/explore?q=%E8%88%B9+%E7%81%A3+%E6%B7%A1%E6%B0%B4+%E6%B9%96&date=2004-01-1+2019-04-11&geo=HK"},{"query":"城門水塘","value":43200,"formattedValue":"飆升","link":"/trends/explore?q=%E5%9F%8E%E9%96%80+%E6%B0%B4+%E5%A1%98&date=2004-01-1+2019-04-11&geo=HK"},{"query":"萬宜大廈","value":21650,"formattedValue":"飆升","link":"/trends/explore?q=%E8%90%AC+%E5%AE%9C+%E5%A4%A7%E5%BB%88&date=2004-01-1+2019-04-11&geo=HK"}]