[{"query":"橫洲工業","value":1070950,"formattedValue":"飆升","link":"/trends/explore?q=%E6%A9%AB+%E6%B4%B2+%E5%B7%A5%E6%A5%AD&date=2004-01-1+2019-04-11&geo=HK"},{"query":"橫洲事件","value":151900,"formattedValue":"飆升","link":"/trends/explore?q=%E6%A9%AB+%E6%B4%B2+%E4%BA%8B%E4%BB%B6&date=2004-01-1+2019-04-11&geo=HK"},{"query":"余文樂","value":91300,"formattedValue":"飆升","link":"/trends/explore?q=%E4%BD%99%E6%96%87%E6%A8%82&date=2004-01-1+2019-04-11&geo=HK"},{"query":"橫洲工業wiki","value":45400,"formattedValue":"飆升","link":"/trends/explore?q=%E6%A9%AB+%E6%B4%B2+%E5%B7%A5%E6%A5%AD+wiki&date=2004-01-1+2019-04-11&geo=HK"}]