[{"query":"大水坑單車公園","value":458500,"formattedValue":"飆升","link":"/trends/explore?q=%E5%A4%A7+%E6%B0%B4+%E5%9D%91+%E5%96%AE%E8%BB%8A+%E5%85%AC%E5%9C%92&date=2004-01-1+2019-04-11&geo=HK"},{"query":"大水坑租單車","value":192950,"formattedValue":"飆升","link":"/trends/explore?q=%E5%A4%A7+%E6%B0%B4+%E5%9D%91+%E7%A7%9F+%E5%96%AE%E8%BB%8A&date=2004-01-1+2019-04-11&geo=HK"},{"query":"大圍租單車","value":23150,"formattedValue":"飆升","link":"/trends/explore?q=%E5%A4%A7+%E5%9C%8D+%E7%A7%9F+%E5%96%AE%E8%BB%8A&date=2004-01-1+2019-04-11&geo=HK"}]